maibench/__init__.py
maibench/cli.py
maibench/completion_fn.py
maibench/grader.py
maibench/test_suite.py
maibench/examples/example_script.py
maibench/utils/data.py
maibenchai-0.2.dist-info/LICENSE
maibenchai-0.2.dist-info/METADATA
maibenchai-0.2.dist-info/WHEEL
maibenchai-0.2.dist-info/top_level.txt
maibenchai-0.2.dist-info/RECORD
