Metadata-Version: 2.1
Name: maibenchai
Version: 0.2
Summary: A simple package for LLM application evaluation.
Author: maibench
Author-email: maibench <support@maibench.ai>
License: MIT License
Project-URL: Homepage, https://maibench.ai
Requires-Python: >=3.7.1
License-File: LICENSE
Requires-Dist: requests >=2.31.0
